llama_index/tools/azure_speech/__init__.py
llama_index/tools/azure_speech/base.py
llama_index_tools_azure_speech-0.4.1.dist-info/METADATA
llama_index_tools_azure_speech-0.4.1.dist-info/WHEEL
llama_index_tools_azure_speech-0.4.1.dist-info/licenses/LICENSE
llama_index_tools_azure_speech-0.4.1.dist-info/RECORD
